esp_idf_size/__init__.py
esp_idf_size/__main__.py
esp_idf_size/core.py
esp_idf_size/chip_info/esp32.yaml
esp_idf_size/chip_info/esp32c2.yaml
esp_idf_size/chip_info/esp32c3.yaml
esp_idf_size/chip_info/esp32c5.yaml
esp_idf_size/chip_info/esp32c6.yaml
esp_idf_size/chip_info/esp32c61.yaml
esp_idf_size/chip_info/esp32h2.yaml
esp_idf_size/chip_info/esp32h4.yaml
esp_idf_size/chip_info/esp32p4.yaml
esp_idf_size/chip_info/esp32s2.yaml
esp_idf_size/chip_info/esp32s3.yaml
esp_idf_size/ng/__init__.py
esp_idf_size/ng/__main__.py
esp_idf_size/ng/deps.py
esp_idf_size/ng/elf.py
esp_idf_size/ng/format_csv.py
esp_idf_size/ng/format_dot.py
esp_idf_size/ng/format_json.py
esp_idf_size/ng/format_raw.py
esp_idf_size/ng/format_table.py
esp_idf_size/ng/format_tree.py
esp_idf_size/ng/log.py
esp_idf_size/ng/main.py
esp_idf_size/ng/mapfile.py
esp_idf_size/ng/memorymap.py
esp_idf_size/ng/docs/readme.md
esp_idf_size-1.6.1.dist-info/LICENSE
esp_idf_size-1.6.1.dist-info/METADATA
esp_idf_size-1.6.1.dist-info/WHEEL
esp_idf_size-1.6.1.dist-info/top_level.txt
esp_idf_size-1.6.1.dist-info/RECORD
