Metadata-Version: 2.1
Name: esp-idf-size
Version: 1.6.1
Summary: Firmware size analysis for ESP-IDF
Home-page: https://github.com/espressif/esp-idf-size
Author: Espressif Systems
Author-email: 
Keywords: espressif,embedded,project,size
Classifier: Development Status :: 5 - Production/Stable
Classifier: Intended Audience :: Developers
Classifier: Natural Language :: English
Classifier: Environment :: Console
Classifier: Topic :: Software Development :: Embedded Systems
Classifier: License :: OSI Approved :: Apache Software License
Classifier: Programming Language :: Python :: 3.7
Classifier: Programming Language :: Python :: 3.8
Classifier: Programming Language :: Python :: 3.9
Classifier: Programming Language :: Python :: 3.10
Classifier: Programming Language :: Python :: 3.11
Classifier: Programming Language :: Python :: 3.12
Classifier: Operating System :: POSIX
Classifier: Operating System :: Microsoft :: Windows
Classifier: Operating System :: MacOS :: MacOS X
Requires-Python: >=3.7
Provides-Extra: dev
License-File: LICENSE
